csrf/__init__.py
csrf/apps.py
csrf/urls.py
csrf/api/__init__.py
csrf/api/urls.py
csrf/api/v1/__init__.py
csrf/api/v1/urls.py
csrf/api/v1/views.py
csrf/tests/__init__.py
csrf/tests/test_api.py
docs/__init__.py
docs/conf.py
edx_rest_framework_extensions/__init__.py
edx_rest_framework_extensions/config.py
edx_rest_framework_extensions/exceptions.py
edx_rest_framework_extensions/middleware.py
edx_rest_framework_extensions/paginators.py
edx_rest_framework_extensions/permissions.py
edx_rest_framework_extensions/settings.py
edx_rest_framework_extensions/utils.py
edx_rest_framework_extensions/auth/__init__.py
edx_rest_framework_extensions/auth/bearer/__init__.py
edx_rest_framework_extensions/auth/bearer/authentication.py
edx_rest_framework_extensions/auth/bearer/tests/__init__.py
edx_rest_framework_extensions/auth/bearer/tests/test_authentication.py
edx_rest_framework_extensions/auth/jwt/__init__.py
edx_rest_framework_extensions/auth/jwt/authentication.py
edx_rest_framework_extensions/auth/jwt/constants.py
edx_rest_framework_extensions/auth/jwt/cookies.py
edx_rest_framework_extensions/auth/jwt/decoder.py
edx_rest_framework_extensions/auth/jwt/middleware.py
edx_rest_framework_extensions/auth/jwt/tests/__init__.py
edx_rest_framework_extensions/auth/jwt/tests/test_authentication.py
edx_rest_framework_extensions/auth/jwt/tests/test_cookies.py
edx_rest_framework_extensions/auth/jwt/tests/test_decoder.py
edx_rest_framework_extensions/auth/jwt/tests/test_middleware.py
edx_rest_framework_extensions/auth/jwt/tests/utils.py
edx_rest_framework_extensions/auth/session/__init__.py
edx_rest_framework_extensions/auth/session/authentication.py
edx_rest_framework_extensions/auth/session/tests/__init__.py
edx_rest_framework_extensions/auth/session/tests/test_authentication.py
edx_rest_framework_extensions/tests/__init__.py
edx_rest_framework_extensions/tests/factories.py
edx_rest_framework_extensions/tests/test_middleware.py
edx_rest_framework_extensions/tests/test_paginators.py
edx_drf_extensions-10.5.0.dist-info/LICENSE.txt
edx_drf_extensions-10.5.0.dist-info/METADATA
edx_drf_extensions-10.5.0.dist-info/WHEEL
edx_drf_extensions-10.5.0.dist-info/top_level.txt
edx_drf_extensions-10.5.0.dist-info/RECORD
